odoo9_addon_l10n_es_aeat_mod349-9.0.2.1.6-nspkg.pth
odoo_addons/l10n_es_aeat_mod349/README.rst
odoo_addons/l10n_es_aeat_mod349/__init__.py
odoo_addons/l10n_es_aeat_mod349/__openerp__.py
odoo_addons/l10n_es_aeat_mod349/hooks.py
odoo_addons/l10n_es_aeat_mod349/data/aeat_349_map_data.xml
odoo_addons/l10n_es_aeat_mod349/data/aeat_export_mod349_data.xml
odoo_addons/l10n_es_aeat_mod349/data/aeat_export_mod349_partner_data.xml
odoo_addons/l10n_es_aeat_mod349/data/aeat_export_mod349_partner_refund_data.xml
odoo_addons/l10n_es_aeat_mod349/docs/BOE-A-2010-5098.pdf
odoo_addons/l10n_es_aeat_mod349/docs/NREG-349-2016.docx
odoo_addons/l10n_es_aeat_mod349/i18n/bg.po
odoo_addons/l10n_es_aeat_mod349/i18n/ca.po
odoo_addons/l10n_es_aeat_mod349/i18n/cs.po
odoo_addons/l10n_es_aeat_mod349/i18n/es.po
odoo_addons/l10n_es_aeat_mod349/i18n/es_CO.po
odoo_addons/l10n_es_aeat_mod349/i18n/es_CR.po
odoo_addons/l10n_es_aeat_mod349/i18n/eu.po
odoo_addons/l10n_es_aeat_mod349/i18n/fr.po
odoo_addons/l10n_es_aeat_mod349/i18n/gl.po
odoo_addons/l10n_es_aeat_mod349/i18n/hr.po
odoo_addons/l10n_es_aeat_mod349/i18n/l10n_es_aeat_mod349.pot
odoo_addons/l10n_es_aeat_mod349/i18n/nl.po
odoo_addons/l10n_es_aeat_mod349/i18n/pl.po
odoo_addons/l10n_es_aeat_mod349/i18n/pt.po
odoo_addons/l10n_es_aeat_mod349/i18n/pt_BR.po
odoo_addons/l10n_es_aeat_mod349/i18n/ru.po
odoo_addons/l10n_es_aeat_mod349/i18n/sl.po
odoo_addons/l10n_es_aeat_mod349/i18n/sv.po
odoo_addons/l10n_es_aeat_mod349/i18n/tr.po
odoo_addons/l10n_es_aeat_mod349/i18n/vi.po
odoo_addons/l10n_es_aeat_mod349/migrations/9.0.2.0.0/post-migration.py
odoo_addons/l10n_es_aeat_mod349/migrations/9.0.2.0.0/pre-migration.py
odoo_addons/l10n_es_aeat_mod349/migrations/9.0.2.1.0/post-migration.py
odoo_addons/l10n_es_aeat_mod349/migrations/9.0.2.1.0/pre-migration.py
odoo_addons/l10n_es_aeat_mod349/models/__init__.py
odoo_addons/l10n_es_aeat_mod349/models/account_invoice.py
odoo_addons/l10n_es_aeat_mod349/models/account_move_line.py
odoo9_addon_l10n_es_aeat_mod349-9.0.2.1.6.dist-info/METADATA
odoo9_addon_l10n_es_aeat_mod349-9.0.2.1.6.dist-info/WHEEL
odoo9_addon_l10n_es_aeat_mod349-9.0.2.1.6.dist-info/namespace_packages.txt
odoo9_addon_l10n_es_aeat_mod349-9.0.2.1.6.dist-info/top_level.txt
odoo9_addon_l10n_es_aeat_mod349-9.0.2.1.6.dist-info/RECORD
