Metadata-Version: 2.1
Name: odoo9-addon-l10n-es-aeat-mod349
Version: 9.0.2.1.6
Summary: Modelo 349 AEAT
Home-page: https://github.com/OCA/l10n-spain
Author: Pexego, Top Consultant, Tecnativa, Eficent, Odoo Community Association (OCA)
Author-email: support@odoo-community.org
License: AGPL-3
Platform: UNKNOWN
Classifier: Programming Language :: Python
Classifier: Framework :: Odoo
Classifier: License :: OSI Approved :: GNU Affero General Public License v3
Requires-Python: ~=2.7
Requires-Dist: odoo9-addon-account-invoice-refund-link
Requires-Dist: odoo9-addon-l10n-es-aeat
Requires-Dist: odoo (<9.1a,>=9.0a)
